[{
  "dateTime" : "04/30/22 00:00:00",
  "value" : "1440"
},{
  "dateTime" : "05/01/22 00:00:00",
  "value" : "1440"
},{
  "dateTime" : "05/02/22 00:00:00",
  "value" : "1440"
},{
  "dateTime" : "05/03/22 00:00:00",
  "value" : "1440"
},{
  "dateTime" : "05/04/22 00:00:00",
  "value" : "1440"
},{
  "dateTime" : "05/05/22 00:00:00",
  "value" : "1372"
},{
  "dateTime" : "05/06/22 00:00:00",
  "value" : "701"
},{
  "dateTime" : "05/07/22 00:00:00",
  "value" : "632"
},{
  "dateTime" : "05/08/22 00:00:00",
  "value" : "668"
},{
  "dateTime" : "05/09/22 00:00:00",
  "value" : "696"
},{
  "dateTime" : "05/10/22 00:00:00",
  "value" : "706"
},{
  "dateTime" : "05/11/22 00:00:00",
  "value" : "676"
},{
  "dateTime" : "05/12/22 00:00:00",
  "value" : "592"
},{
  "dateTime" : "05/13/22 00:00:00",
  "value" : "653"
},{
  "dateTime" : "05/14/22 00:00:00",
  "value" : "602"
},{
  "dateTime" : "05/15/22 00:00:00",
  "value" : "746"
},{
  "dateTime" : "05/16/22 00:00:00",
  "value" : "692"
},{
  "dateTime" : "05/17/22 00:00:00",
  "value" : "837"
},{
  "dateTime" : "05/18/22 00:00:00",
  "value" : "658"
},{
  "dateTime" : "05/19/22 00:00:00",
  "value" : "610"
},{
  "dateTime" : "05/20/22 00:00:00",
  "value" : "878"
},{
  "dateTime" : "05/21/22 00:00:00",
  "value" : "777"
},{
  "dateTime" : "05/22/22 00:00:00",
  "value" : "821"
},{
  "dateTime" : "05/23/22 00:00:00",
  "value" : "692"
},{
  "dateTime" : "05/24/22 00:00:00",
  "value" : "727"
},{
  "dateTime" : "05/25/22 00:00:00",
  "value" : "733"
},{
  "dateTime" : "05/26/22 00:00:00",
  "value" : "802"
},{
  "dateTime" : "05/27/22 00:00:00",
  "value" : "654"
},{
  "dateTime" : "05/28/22 00:00:00",
  "value" : "827"
},{
  "dateTime" : "05/29/22 00:00:00",
  "value" : "745"
}]