[{
  "dateTime" : "02/19/24 00:00:00",
  "value" : "1058"
},{
  "dateTime" : "02/20/24 00:00:00",
  "value" : "706"
},{
  "dateTime" : "02/21/24 00:00:00",
  "value" : "592"
},{
  "dateTime" : "02/22/24 00:00:00",
  "value" : "830"
},{
  "dateTime" : "02/23/24 00:00:00",
  "value" : "749"
},{
  "dateTime" : "02/24/24 00:00:00",
  "value" : "661"
},{
  "dateTime" : "02/25/24 00:00:00",
  "value" : "1316"
},{
  "dateTime" : "02/26/24 00:00:00",
  "value" : "746"
},{
  "dateTime" : "02/27/24 00:00:00",
  "value" : "1295"
},{
  "dateTime" : "02/28/24 00:00:00",
  "value" : "1301"
},{
  "dateTime" : "02/29/24 00:00:00",
  "value" : "1373"
},{
  "dateTime" : "03/01/24 00:00:00",
  "value" : "1172"
},{
  "dateTime" : "03/02/24 00:00:00",
  "value" : "755"
},{
  "dateTime" : "03/03/24 00:00:00",
  "value" : "907"
},{
  "dateTime" : "03/04/24 00:00:00",
  "value" : "799"
},{
  "dateTime" : "03/05/24 00:00:00",
  "value" : "782"
},{
  "dateTime" : "03/06/24 00:00:00",
  "value" : "1440"
},{
  "dateTime" : "03/07/24 00:00:00",
  "value" : "1440"
},{
  "dateTime" : "03/08/24 00:00:00",
  "value" : "855"
},{
  "dateTime" : "03/09/24 00:00:00",
  "value" : "807"
},{
  "dateTime" : "03/10/24 00:00:00",
  "value" : "820"
},{
  "dateTime" : "03/11/24 00:00:00",
  "value" : "886"
},{
  "dateTime" : "03/12/24 00:00:00",
  "value" : "955"
},{
  "dateTime" : "03/13/24 00:00:00",
  "value" : "1440"
},{
  "dateTime" : "03/14/24 00:00:00",
  "value" : "1440"
},{
  "dateTime" : "03/15/24 00:00:00",
  "value" : "1339"
},{
  "dateTime" : "03/16/24 00:00:00",
  "value" : "1143"
},{
  "dateTime" : "03/17/24 00:00:00",
  "value" : "1440"
},{
  "dateTime" : "03/18/24 00:00:00",
  "value" : "1434"
},{
  "dateTime" : "03/19/24 00:00:00",
  "value" : "1305"
}]